livekit/plugins/bithuman/__init__.py
livekit/plugins/bithuman/avatar.py
livekit/plugins/bithuman/log.py
livekit/plugins/bithuman/py.typed
livekit/plugins/bithuman/version.py
livekit_plugins_bithuman-1.3.11.dist-info/METADATA
livekit_plugins_bithuman-1.3.11.dist-info/WHEEL
livekit_plugins_bithuman-1.3.11.dist-info/RECORD
