Metadata-Version: 2.4
Name: livekit-plugins-bithuman
Version: 1.3.11
Summary: Agent Framework plugin for services from BitHuman Avatar Rendering
Project-URL: Documentation, https://docs.livekit.io
Project-URL: Website, https://livekit.io/
Project-URL: Source, https://github.com/livekit/agents
Author-email: LiveKit <support@livekit.io>
License-Expression: Apache-2.0
Keywords: ai,audio,livekit,realtime,video,voice,webrtc
Classifier: Intended Audience :: Developers
Classifier: License :: OSI Approved :: Apache Software License
Classifier: Programming Language :: Python :: 3
Classifier: Programming Language :: Python :: 3 :: Only
Classifier: Programming Language :: Python :: 3.10
Classifier: Topic :: Multimedia :: Sound/Audio
Classifier: Topic :: Multimedia :: Video
Classifier: Topic :: Scientific/Engineering :: Artificial Intelligence
Requires-Python: >=3.9.0
Requires-Dist: bithuman>=0.5.25
Requires-Dist: livekit-agents>=1.3.11
